snowauth/__init__.py
snowauth/snowauth.py
snowauth-1.0.2.dist-info/METADATA
snowauth-1.0.2.dist-info/WHEEL
snowauth-1.0.2.dist-info/top_level.txt
snowauth-1.0.2.dist-info/RECORD
