Metadata-Version: 2.1
Name: snowauth
Version: 1.0.2
Summary: A package for the simple local management of snowpark for python connections.
Home-page: https://github.com/sfc-gh-dwilczak/snowauth
Author: Branden Ciranni, Daniel Wilczak
Author-email: daniel.wilczak@snowflake.com
License: mit
Keywords: Snowflake,Snowpark
Classifier: Topic :: Printing
Classifier: Development Status :: 5 - Production/Stable
Classifier: License :: OSI Approved :: MIT License
Classifier: Programming Language :: Python :: 3.8
Classifier: Programming Language :: Python :: 3.9
Classifier: Programming Language :: Python :: 3.10
Classifier: Operating System :: OS Independent
Classifier: Intended Audience :: Developers
Requires-Python: <3.11,>=3.8
Requires-Dist: snowflake-snowpark-python
Requires-Dist: toml
